birtodo/__init__.py
birtodo/__main__.py
birtodo/app.py
birtodo/database.py
birtodo/exceptions.py
birtodo-0.1.0.dist-info/entry_points.txt
birtodo-0.1.0.dist-info/WHEEL
birtodo-0.1.0.dist-info/METADATA
birtodo-0.1.0.dist-info/RECORD
